AUTHORS.rst
CHANGELOG.rst
LICENSE
MANIFEST.in
README.rst
sample.vcl
setup.py
cache_headers/__init__.py
cache_headers/__init__.pyc
cache_headers/middleware.py
cache_headers/middleware.pyc
cache_headers/models.py
cache_headers/models.pyc
cache_headers/policies.py
cache_headers/policies.pyc
cache_headers/utils.py
cache_headers/utils.pyc
cache_headers/management/__init__.py
cache_headers/management/__init__.pyc
cache_headers/management/commands/__init__.py
cache_headers/management/commands/__init__.pyc
cache_headers/management/commands/generate_vcl.py
cache_headers/management/commands/generate_vcl.pyc
cache_headers/tests/__init__.py
cache_headers/tests/manage.py
cache_headers/tests/policies.py
cache_headers/tests/test_middleware.py
cache_headers/tests/urls.py
cache_headers/tests/views.py
cache_headers/tests/requirements/110.txt
cache_headers/tests/requirements/111.txt
cache_headers/tests/requirements/20.txt
cache_headers/tests/settings/110.py
cache_headers/tests/settings/111.py
cache_headers/tests/settings/20.py
cache_headers/tests/settings/__init__.py
cache_headers/tests/settings/__init__.pyc
cache_headers/tests/templates/tests/view.html
django_cache_headers.egg-info/PKG-INFO
django_cache_headers.egg-info/SOURCES.txt
django_cache_headers.egg-info/dependency_links.txt
django_cache_headers.egg-info/not-zip-safe
django_cache_headers.egg-info/requires.txt
django_cache_headers.egg-info/top_level.txt