Metadata-Version: 1.1
Name: django-cache-headers
Version: 0.4
Summary: Configurable middleware to add HTTP caching headers for URL's.
Home-page: http://github.com/praekelt/django-cache-headers
Author: Praekelt Consulting
Author-email: dev@praekelt.com
License: BSD
Platform: UNKNOWN
Classifier: Programming Language :: Python
Classifier: License :: OSI Approved :: BSD License
Classifier: Operating System :: OS Independent
Classifier: Framework :: Django
Classifier: Intended Audience :: Developers
Classifier: Topic :: Internet :: WWW/HTTP :: Dynamic Content
